mochow_mcp_server/__init__.py
mochow_mcp_server/server.py
mochow_mcp_server-1.0.1.dist-info/LICENSE
mochow_mcp_server-1.0.1.dist-info/METADATA
mochow_mcp_server-1.0.1.dist-info/WHEEL
mochow_mcp_server-1.0.1.dist-info/entry_points.txt
mochow_mcp_server-1.0.1.dist-info/top_level.txt
mochow_mcp_server-1.0.1.dist-info/RECORD
