Metadata-Version: 2.1
Name: mochow-mcp-server
Version: 1.0.1
Summary: MCP server for Mochow vector database
Author-email: caoshili <caoshili@baidu.com>
License: Apache-2.0
Requires-Python: >=3.10
License-File: LICENSE
Requires-Dist: mcp[cli] >=1.1.2
Requires-Dist: pymochow >=2.2.7
Requires-Dist: dotenv >=0.9.9
